{
  "id": "article-refresh-pagination",
  "name": "article-refresh-pagination",
  "title": "检查并修复新文章提示、筛选和分页逻辑",
  "description": "",
  "status": "completed",
  "dev_type": null,
  "scope": null,
  "package": null,
  "priority": "P2",
  "creator": "Maplume",
  "assignee": "Maplume",
  "createdAt": "2026-06-07",
  "completedAt": "2026-06-07",
  "branch": null,
  "base_branch": "MaplumeX/krakow",
  "worktree_path": null,
  "commit": null,
  "pr_url": null,
  "subtasks": [],
  "children": [],
  "parent": null,
  "relatedFiles": [],
  "notes": "",
  "meta": {}
}