{
  "id": "make-add-feed-endpoint-async-background",
  "name": "make-add-feed-endpoint-async-background",
  "title": "Make add-feed endpoint async background",
  "description": "",
  "status": "completed",
  "dev_type": null,
  "scope": null,
  "package": null,
  "priority": "P2",
  "creator": "Maplume",
  "assignee": "Maplume",
  "createdAt": "2026-06-03",
  "completedAt": "2026-06-03",
  "branch": null,
  "base_branch": "MaplumeX/fix-slow-feed-subscription",
  "worktree_path": null,
  "commit": null,
  "pr_url": null,
  "subtasks": [],
  "children": [],
  "parent": null,
  "relatedFiles": [],
  "notes": "",
  "meta": {}
}