{
  "id": "improve-scroll-mark-as-read-accuracy-with-intersectionobserver",
  "name": "improve-scroll-mark-as-read-accuracy-with-intersectionobserver",
  "title": "Improve scroll mark-as-read accuracy with IntersectionObserver",
  "description": "",
  "status": "completed",
  "dev_type": null,
  "scope": null,
  "package": null,
  "priority": "P2",
  "creator": "Maplume",
  "assignee": "Maplume",
  "createdAt": "2026-06-03",
  "completedAt": "2026-06-04",
  "branch": null,
  "base_branch": "MaplumeX/fix-scroll-read-boundary",
  "worktree_path": null,
  "commit": null,
  "pr_url": null,
  "subtasks": [],
  "children": [],
  "parent": null,
  "relatedFiles": [],
  "notes": "",
  "meta": {}
}